{
  "image_index": 176,
  "split": "new",
  "relationships": {
    "left": [
      [],
      [
        0
      ],
      [
        0,
        1
      ],
      [
        0,
        1,
        2
      ]
    ],
    "front": [
      [
        1,
        2
      ],
      [
        2
      ],
      [],
      [
        0,
        1,
        2
      ]
    ],
    "behind": [
      [
        3
      ],
      [
        0,
        3
      ],
      [
        0,
        1,
        3
      ],
      []
    ],
    "right": [
      [
        1,
        2,
        3
      ],
      [
        2,
        3
      ],
      [
        3
      ],
      []
    ]
  },
  "directions": {
    "left": [
      -0.6563112735748291,
      -0.7544902563095093,
      0.0
    ],
    "behind": [
      -0.754490315914154,
      0.6563112735748291,
      0.0
    ],
    "below": [
      -0.0,
      -0.0,
      -1.0
    ],
    "front": [
      0.754490315914154,
      -0.6563112735748291,
      -0.0
    ],
    "above": [
      0.0,
      0.0,
      1.0
    ],
    "right": [
      0.6563112735748291,
      0.7544902563095093,
      -0.0
    ]
  },
  "image_filename": "CLEVR_new_000176",
  "objects": [
    {
      "rotation": 75.6938657279126,
      "material": "metal",
      "color": "blue",
      "3d_coords": [
        -1.4371027946472168,
        -0.20877955853939056,
        0.3499999940395355
      ],
      "shape": "sphere",
      "pixel_coords": [
        128,
        98,
        11.931550025939941
      ],
      "size": "small"
    },
    {
      "rotation": 357.61509646419717,
      "material": "rubber",
      "color": "yellow",
      "3d_coords": [
        -0.3385271430015564,
        0.4001901149749756,
        0.3499999940395355
      ],
      "shape": "cube",
      "pixel_coords": [
        162,
        103,
        11.553731918334961
      ],
      "size": "small"
    },
    {
      "rotation": 304.5741796394486,
      "material": "rubber",
      "color": "blue",
      "3d_coords": [
        2.5951998233795166,
        -0.5499224066734314,
        0.699999988079071
      ],
      "shape": "sphere",
      "pixel_coords": [
        211,
        139,
        8.890236854553223
      ],
      "size": "large"
    },
    {
      "rotation": 90.90476049056876,
      "material": "rubber",
      "color": "gray",
      "3d_coords": [
        -0.533035933971405,
        2.7864127159118652,
        0.3499999940395355
      ],
      "shape": "sphere",
      "pixel_coords": [
        207,
        83,
        13.061566352844238
      ],
      "size": "small"
    }
  ]
}